alu.v
module alu(

input [7:0] A,
input [7:0] B,

input [2:0] Op,

output reg [7:0] Result,
output reg Carry

);

always @(*) begin

Carry=0;

case(Op)

3'b000:
{Carry,Result}=A+B;

3'b001:
{Carry,Result}=A-B;

3'b010:
Result=A&B;

3'b011:
Result=A|B;

3'b100:
Result=A^B;

3'b101:
Result=~A;

default:
Result=8'b00000000;

endcase

end

endmodule

register.v
module registerfile(
    input CLK,
    input RESET,
    input WE,
    
    //write data
    input [2:0] write_addr,
    input [7:0] write_data,

    //read data
    input [2:0] read_addr1,
    input [2:0] read_addr2,

    output [7:0] read_data1,
    output [7:0] read_data2
);

reg [7:0] REGS [0:7];
integer i;

always @(posedge CLK) begin
    if (RESET) begin
        for (i = 0; i < 8; i = i + 1)
            REGS[i] <= 8'b0;
    end
    else if (WE)
        REGS[write_addr] <= write_data;
end

assign read_data1 = REGS[read_addr1];
assign read_data2 = REGS[read_addr2];

endmodule

controlunit.v
module controlunit(
input [15:0]instruction,

output reg[2:0] alu_op,
output reg[2:0]rd,
output reg[2:0]Rs1,
output reg[2:0]Rs2,

output reg WE,
output reg  HALT
);
always @(*)begin
    HALT = 1'b0;
    WE  = 1'b0;
    alu_op = 3'b000;
    rd=instruction[11:9];
    Rs1=instruction[8:6];
    Rs2=instruction[5:3];    
    case (instruction[15:12])
    4'b1111: begin
        HALT = 1'b1;
        WE  = 1'b0;
    end
    4'b0001:begin
        alu_op=3'b000; // ADD //translating to alu 
       
        WE=1'b1;
    end

    4'b0010:begin
        alu_op=3'b001; // SUB
       
        WE=1'b1;

    end

    4'b0011:begin
        alu_op=3'b010; // AND
       
        WE=1'b1;
    end

    4'b0100:begin
        alu_op=3'b011; // OR
       
        WE=1'b1;
    end

    4'b0101:begin
        alu_op=3'b100; // XOR
       
        WE=1'b1;
    end

    4'b0110:begin
        alu_op=3'b101; // NOT
       
        WE=1'b1;
    end
    4'b0111: begin

        alu_op = 3'b000;   // Not used for LOAD
        WE     = 1;
        HALT   = 0;
    end

        default: begin

    alu_op = 3'b000;
    rd     = 3'b000;
    Rs1    = 3'b000;
    Rs2    = 3'b000;
    WE     = 0;
    HALT   = 0;

end
    endcase

end

endmodule

instruction_memory.v
module instruction_memory(
    input [3:0] Address,
    output [15:0]instruction

);
//Instruction Memory stores an array of instructions.
    reg [15:0] MEM[15:0];          
/*15          12 11      9 8       6 5       3 2      0
+---------------+---------+---------+---------+--------+
|    Opcode     |   Rd    |   Rs1   |   Rs2   |Unused  |
+---------------+---------+---------+---------+--------+*/
    initial begin
    $readmemb("progrem.mem", MEM);       

    end
    assign instruction=MEM[Address];  
endmodule

/* menuel instruction input
MEM[0] = 16'b0111__000100001011; // LOAD R1,#10
MEM[1] = 16'b0111_010_000010101; // LOAD R2,#20
MEM[2] = 16'b0001_011_001_010_000; // ADD R3,R1,R2
MEM[3] = 16'b1111_000_000000000; // HALT*/

counter.v
module counter(

input CLK,
input RESET,
input HALT,
output reg [3:0] PC

);

always @(posedge CLK)
begin

    if(RESET)
        PC <= 8'd0; //start for first instruction

    else if(!HALT)
        PC <= PC + 1;

end

endmodule

cpu.v
module cpu(
input CLK,
input RESET
);
//counter
wire [3:0] pc;

//instruction memory
wire [15:0]instruction;

//control unit
wire[2:0] alu_op;
wire[2:0]rd;
wire[2:0]Rs1;
wire[2:0]Rs2;
wire WE;
wire  HALT;

//register
wire [7:0] read_data1;
wire [7:0] read_data2;
//alu
wire [7:0] Result;
wire Carry;

wire [7:0] immediate;
wire [7:0] write_data;

assign immediate = instruction[7:0]; 
/*15          12 11      9 8                0
+---------------+---------+-----------------+
|    Opcode     |   Rd    |   Immediate     |
+---------------+---------+-----------------+*/
assign write_data =
    (instruction[15:12] == 4'b0111) ? //multiplexer for load
        immediate :
        Result;

counter pc1(
    .PC(pc),
    .CLK(CLK),
    .RESET(RESET),
    .HALT(HALT)
);
instruction_memory im(
    .Address(pc),
    .instruction(instruction)
);
controlunit cu(
    .instruction(instruction),
    .alu_op(alu_op),
    .rd(rd),
    .Rs1(Rs1),
    .Rs2(Rs2),

    .WE(WE),
    .HALT(HALT)
);
registerfile rf(
    .CLK(CLK),
    .RESET(RESET),
    .WE(WE),
    .read_addr1(Rs1),
    .read_addr2(Rs2),
    .write_addr(rd),
    .write_data(write_data),
    .read_data1(read_data1),
    .read_data2(read_data2)
);
alu al(
    .Result(Result),
    .Carry(Carry),
    .A(read_data1),
    .B(read_data2),
    .Op(alu_op)
);

endmodule

cpu_tb.v
module cpu_tb;

reg CLK;
reg RESET;

cpu uut(

    .CLK(CLK),
    .RESET(RESET)

);

// Clock Generation
always #5 CLK = ~CLK;

// Test
initial begin

    CLK = 0;
    RESET = 1;

    #10;

    RESET = 0;

    #200;

    $finish;

end

// Monitor
initial begin

$monitor("Time= %2t | PC= %d | Instruction= %b | Result= %2d",
$time,
uut.pc,
uut.instruction,
uut.Result);
$dumpfile("cpu.vcd");
$dumpvars(0, cpu_tb);

end

endmodule

cpu.vcd
$date
	Fri Jul 31 09:07:04 2026
$end
$version
	Icarus Verilog
$end
$timescale
	1s
$end
$scope module cpu_tb $end
$var reg 1 ! CLK $end
$var reg 1 " RESET $end
$scope module uut $end
$var wire 1 ! CLK $end
$var wire 1 " RESET $end
$var wire 8 # write_data [7:0] $end
$var wire 8 $ read_data2 [7:0] $end
$var wire 8 % read_data1 [7:0] $end
$var wire 3 & rd [2:0] $end
$var wire 4 ' pc [3:0] $end
$var wire 16 ( instruction [15:0] $end
$var wire 8 ) immediate [7:0] $end
$var wire 3 * alu_op [2:0] $end
$var wire 1 + WE $end
$var wire 3 , Rs2 [2:0] $end
$var wire 3 - Rs1 [2:0] $end
$var wire 8 . Result [7:0] $end
$var wire 1 / HALT $end
$var wire 1 0 Carry $end
$scope module al $end
$var wire 3 1 Op [2:0] $end
$var wire 8 2 B [7:0] $end
$var wire 8 3 A [7:0] $end
$var reg 1 0 Carry $end
$var reg 8 4 Result [7:0] $end
$upscope $end
$scope module cu $end
$var wire 16 5 instruction [15:0] $end
$var reg 1 / HALT $end
$var reg 3 6 Rs1 [2:0] $end
$var reg 3 7 Rs2 [2:0] $end
$var reg 1 + WE $end
$var reg 3 8 alu_op [2:0] $end
$var reg 3 9 rd [2:0] $end
$upscope $end
$scope module im $end
$var wire 16 : instruction [15:0] $end
$var wire 4 ; Address [3:0] $end
$upscope $end
$scope module pc1 $end
$var wire 1 ! CLK $end
$var wire 1 / HALT $end
$var wire 1 " RESET $end
$var reg 4 < PC [3:0] $end
$upscope $end
$scope module rf $end
$var wire 1 ! CLK $end
$var wire 1 " RESET $end
$var wire 1 + WE $end
$var wire 3 = read_addr1 [2:0] $end
$var wire 3 > read_addr2 [2:0] $end
$var wire 8 ? read_data1 [7:0] $end
$var wire 8 @ read_data2 [7:0] $end
$var wire 3 A write_addr [2:0] $end
$var wire 8 B write_data [7:0] $end
$var integer 32 C i [31:0] $end
$upscope $end
$upscope $end
$upscope $end
$enddefinitions $end
$comment Show the parameter values. $end
$dumpall
$end
#0
$dumpvars
bx C
bx B
bx A
bx @
bx ?
bx >
bx =
bx <
bx ;
bx :
bx 9
bx 8
bx 7
bx 6
bx 5
bx 4
bx 3
bx 2
bx 1
x0
x/
bx .
bx -
bx ,
x+
bx *
bx )
bx (
bx '
bx &
bx %
bx $
bx #
1"
0!
$end
#5
b1010 #
b1010 B
b0 .
b0 4
00
b1010 )
b0 $
b0 2
b0 @
b1 ,
b1 7
b1 >
b0 %
b0 3
b0 ?
b0 -
b0 6
b0 =
b1 &
b1 9
b1 A
b0 *
b0 1
b0 8
1+
0/
b111001000001010 (
b111001000001010 5
b111001000001010 :
b0 '
b0 ;
b0 <
b1000 C
1!
#10
0!
0"
#15
b10100 #
b10100 B
b10100 )
b10 ,
b10 7
b10 >
b10 &
b10 9
b10 A
1+
b0 $
b0 2
b0 @
b111010000010100 (
b111010000010100 5
b111010000010100 :
b1 '
b1 ;
b1 <
1!
#20
0!
#25
b11110 #
b11110 B
b1010000 )
b1010 %
b1010 3
b1010 ?
b1 -
b1 6
b1 =
b11 &
b11 9
b11 A
1+
b11110 .
b11110 4
b1011001010000 (
b1011001010000 5
b1011001010000 :
b10 '
b10 ;
b10 <
b10100 $
b10100 2
b10100 @
1!
#30
0!
#35
b11110110 #
b11110110 B
10
b11110110 .
b11110110 4
b1 *
b1 1
b1 8
b100 &
b100 9
b100 A
1+
b10100001010000 (
b10100001010000 5
b10100001010000 :
b11 '
b11 ;
b11 <
1!
#40
0!
#45
b11110101 #
b11110101 B
b11110101 .
b11110101 4
00
b1000000 )
b0 $
b0 2
b0 @
b0 ,
b0 7
b0 >
b101 &
b101 9
b101 A
b101 *
b101 1
b101 8
1+
b110101001000000 (
b110101001000000 5
b110101001000000 :
b100 '
b100 ;
b100 <
1!
#50
0!
#55
b0 #
b0 B
b0 .
b0 4
b0 )
1/
b0 %
b0 3
b0 ?
b0 -
b0 6
b0 =
b0 &
b0 9
b0 A
b0 *
b0 1
b0 8
0+
b1111000000000000 (
b1111000000000000 5
b1111000000000000 :
b101 '
b101 ;
b101 <
1!
